beautiful_cookiecutter/VERSION.txt
beautiful_cookiecutter/__init__.py
beautiful_cookiecutter/__main__.py
beautiful_cookiecutter/cli.py
beautiful_cookiecutter-0.1.1.dist-info/LICENSE
beautiful_cookiecutter-0.1.1.dist-info/METADATA
beautiful_cookiecutter-0.1.1.dist-info/WHEEL
beautiful_cookiecutter-0.1.1.dist-info/RECORD
