Metadata-Version: 2.1
Name: beautiful-cookiecutter
Version: 0.1.1
Summary: 
Author: Sergey Kuzin
Author-email: serge@kuzin.name
Requires-Python: >=3.11,<4.0
Classifier: Programming Language :: Python :: 3
Classifier: Programming Language :: Python :: 3.11
Classifier: Programming Language :: Python :: 3.12
Requires-Dist: poetry2setup (>=1.1.0,<2.0.0)
